setup.py
POC_T.egg-info/PKG-INFO
POC_T.egg-info/SOURCES.txt
POC_T.egg-info/dependency_links.txt
POC_T.egg-info/not-zip-safe
POC_T.egg-info/requires.txt
POC_T.egg-info/top_level.txt
lib/__init__.py
lib/cli.py
lib/debug.py
lib/api/__init__.py
lib/api/shodan/__init__.py
lib/api/shodan/query.py
lib/api/zoomeye/__init__.py
lib/api/zoomeye/search.py
lib/api/zoomeye/zoomeye.py
lib/controller/__init__.py
lib/controller/api.py
lib/controller/engine.py
lib/controller/loader.py
lib/core/__init__.py
lib/core/common.py
lib/core/convert.py
lib/core/data.py
lib/core/datatype.py
lib/core/enums.py
lib/core/exception.py
lib/core/log.py
lib/core/option.py
lib/core/register.py
lib/core/revision.py
lib/core/settings.py
lib/parse/__init__.py
lib/parse/cmdline.py
lib/utils/__init__.py
lib/utils/cnhelp.py
lib/utils/consle.py
lib/utils/update.py
lib/utils/versioncheck.py
plugin/__init__.py
plugin/cloudeye.py
plugin/extracts.py
plugin/static.py
plugin/urlparser.py
plugin/useragent.py
plugin/util.py
script/__init__.py
script/activemq-upload.py
script/activemq-weakpass.py
script/bingc.py
script/brute-example.py
script/confluence-file-read.py
script/jboss-rce.py
script/opensshd-user-enum.py
script/redis-cron-getshell.py
script/redis-sshkey-getshell.py
script/redis-unauth.py
script/redis-web-probe.py
script/solr-unauth.py
script/spider-example.py
script/struts2-devmode.py
script/struts2-s2032.py
script/test.py
script/vote-example.py
script/weblogic-ssrf-netmap.py
script/zabbix-weakpass.py
script/zonetransfer-poc.py
thirdparty/__init__.py
thirdparty/IPy/IPy.py
thirdparty/IPy/__init__.py
thirdparty/ansistrm/__init__.py
thirdparty/ansistrm/ansistrm.py
thirdparty/colorama/__init__.py
thirdparty/colorama/ansi.py
thirdparty/colorama/ansitowin32.py
thirdparty/colorama/initialise.py
thirdparty/colorama/win32.py
thirdparty/colorama/winterm.py
thirdparty/odict/__init__.py
thirdparty/odict/odict.py
thirdparty/termcolor/__init__.py
thirdparty/termcolor/termcolor.py